{"frameRate":30,"armature":[{"ik":[],"type":"Armature","frameRate":30,"slot":[{"displayIndex":-1,"name":"moshui","parent":"chi","color":{}},{"z":1,"name":"modi","parent":"chi","color":{}},{"z":2,"displayIndex":1,"name":"mo","parent":"mo","color":{}},{"z":3,"displayIndex":-1,"name":"chi","parent":"chi","color":{}},{"blendMode":"add","displayIndex":-1,"z":4,"parent":"szi","name":"chig","color":{}},{"blendMode":"add","displayIndex":-1,"z":5,"parent":"guang1","name":"guang","color":{}}],"aabb":{"width":128,"y":-64,"height":128,"x":-63.12},"defaultActions":[{"gotoAndPlay":"fei"}],"bone":[{"name":"root","transform":{}},{"transform":{},"name":"zti","parent":"root"},{"transform":{"skX":-90,"skY":-90},"name":"chi","parent":"zti"},{"transform":{"y":9.7786,"skX":-90,"skY":-90,"x":1.3238},"name":"boom1","parent":"zti"},{"transform":{"y":8.8,"skX":-90,"skY":-90,"x":-3.1406},"name":"guang","parent":"zti"},{"transform":{"y":9.75,"skX":-90,"skY":-90,"x":5.2},"name":"szi","parent":"zti"},{"transform":{"y":20,"skX":-90,"skY":-90,"x":20},"name":"chi1","parent":"zti"},{"length":61,"transform":{"y":0.1771,"x":2.343},"parent":"guang","name":"guang1"},{"length":39,"transform":{"y":0.4754,"x":0.5086},"parent":"chi","name":"mo"}],"name":"Armature","skin":[{"name":"","slot":[{"display":[{"type":"image","name":"mo","transform":{"y":-0.3246,"skX":90,"skY":90,"x":-0.3255}},{"type":"image","name":"moji","transform":{"y":0.4046,"skX":90,"skY":90,"x":-0.5086}}],"name":"mo"},{"display":[{"type":"image","name":"guang","transform":{"y":-0.2021,"skX":90,"skY":90,"x":-0.0221}}],"blendMode":"add","name":"guang"},{"display":[{"type":"image","name":"modi","transform":{"y":-3.6733,"skX":90,"skY":90,"x":-5.3443}}],"name":"modi"},{"display":[{"type":"image","name":"chig","transform":{"y":-5.2,"skX":90,"skY":90,"x":14.3}},{"type":"image","name":"zhaog","transform":{"y":-5.2,"skX":90,"skY":90,"x":9.75}},{"type":"image","name":"pengg","transform":{"y":-5.2,"skX":90,"skY":90,"x":9.75}},{"type":"image","name":"longg","transform":{"y":-5.2,"skX":90,"skY":90,"x":9.75}}],"blendMode":"add","name":"chig"},{"display":[{"type":"image","name":"moshui","transform":{"y":-4.2364,"skX":90,"skY":90,"x":-0.9637}}],"name":"moshui"},{"display":[{"type":"image","name":"chi","transform":{"skX":90,"skY":90}},{"type":"image","name":"hu","transform":{"skX":90,"skY":90}},{"type":"image","name":"long","transform":{"skX":90,"skY":90}},{"type":"image","name":"peng","transform":{"skX":90,"skY":90}},{"type":"image","name":"zhao","transform":{"skX":90,"skY":90}}],"name":"chi"}]}],"animation":[{"ffd":[],"frame":[],"playTimes":0,"duration":45,"bone":[{"frame":[{"tweenEasing":null,"transform":{},"duration":45}],"name":"root"},{"frame":[{"curve":[0.234,0.008,1,1],"transform":{"scX":1.5,"scY":1.5},"duration":5},{"tweenEasing":0,"transform":{"scX":0.3957,"scY":0.3957},"duration":5},{"tweenEasing":0,"transform":{"scX":1.4175,"scY":1.4175,"x":1.13},"duration":10},{"tweenEasing":0,"transform":{},"duration":25},{"tweenEasing":null,"transform":{},"duration":0}],"name":"chi"},{"frame":[{"tweenEasing":null,"transform":{"scX":0.4856,"scY":0.4856},"duration":4},{"tweenEasing":0,"transform":{"scX":0.4856,"scY":0.4856},"duration":7},{"tweenEasing":0,"transform":{"scX":1.5017,"y":6.3275,"scY":1.5017,"x":2.1},"duration":13},{"tweenEasing":null,"transform":{"scX":1.525,"y":1.0062,"scY":1.525,"x":1.05},"duration":21}],"name":"szi"},{"frame":[{"tweenEasing":null,"transform":{},"duration":4},{"curve":[0,0,0.81,0.995],"transform":{"scX":0.01,"y":7.7437,"scY":0.01,"x":-5.1625},"duration":28},{"tweenEasing":null,"transform":{"scX":1.9744,"y":5.19,"scY":1.9744,"x":-5.19},"duration":13}],"name":"mo"},{"frame":[{"tweenEasing":null,"transform":{},"duration":45}],"name":"guang1"},{"frame":[{"tweenEasing":null,"transform":{},"duration":45}],"name":"zti"},{"frame":[{"tweenEasing":null,"transform":{},"duration":45}],"name":"boom1"},{"frame":[{"tweenEasing":null,"transform":{},"duration":45}],"name":"guang"},{"frame":[{"tweenEasing":null,"transform":{},"duration":45}],"name":"chi1"}],"name":"fei","slot":[{"frame":[{"color":{},"displayIndex":-1,"tweenEasing":null,"duration":45}],"name":"moshui"},{"frame":[{"color":{},"tweenEasing":null,"duration":45}],"name":"modi"},{"frame":[{"color":{"aM":0},"displayIndex":1,"tweenEasing":null,"duration":6},{"color":{"aM":0},"displayIndex":1,"tweenEasing":0,"duration":1},{"color":{"aM":80},"displayIndex":1,"tweenEasing":null,"duration":13},{"color":{"aM":80},"displayIndex":1,"tweenEasing":0,"duration":11},{"color":{"aM":0},"displayIndex":1,"tweenEasing":null,"duration":14}],"name":"mo"},{"frame":[{"color":{},"tweenEasing":null,"duration":45}],"name":"chi"},{"frame":[{"color":{"rM":91,"gM":54,"bM":33,"aM":0},"tweenEasing":null,"duration":4},{"color":{"rM":91,"gM":54,"bM":33,"aM":0},"tweenEasing":0,"duration":3},{"color":{"rM":91,"gM":54,"bM":33},"tweenEasing":null,"duration":9},{"color":{"rM":91,"gM":54,"bM":33},"tweenEasing":0,"duration":7},{"color":{"rM":91,"gM":54,"bM":33,"aM":0},"tweenEasing":null,"duration":22}],"name":"chig"},{"frame":[{"color":{},"displayIndex":-1,"tweenEasing":null,"duration":45}],"name":"guang"}]},{"ffd":[],"frame":[],"playTimes":0,"duration":45,"bone":[{"frame":[{"tweenEasing":null,"transform":{},"duration":45}],"name":"root"},{"frame":[{"curve":[0.234,0.008,1,1],"transform":{"scX":1.5,"scY":1.5},"duration":5},{"tweenEasing":0,"transform":{"scX":0.3957,"scY":0.3957},"duration":5},{"tweenEasing":0,"transform":{"scX":1.4175,"scY":1.4175,"x":1.13},"duration":10},{"tweenEasing":0,"transform":{},"duration":25},{"tweenEasing":null,"transform":{},"duration":0}],"name":"chi"},{"frame":[{"tweenEasing":null,"transform":{"scX":0.4856,"scY":0.4856},"duration":4},{"tweenEasing":0,"transform":{"scX":0.4856,"scY":0.4856},"duration":7},{"tweenEasing":0,"transform":{"scX":1.3434,"scY":1.3434,"x":4.0968},"duration":13},{"tweenEasing":null,"transform":{"scX":1.5915,"y":2.0262,"scY":1.5915,"x":3.93},"duration":21}],"name":"szi"},{"frame":[{"tweenEasing":null,"transform":{},"duration":4},{"curve":[0,0,0.81,0.995],"transform":{"scX":0.01,"y":7.7437,"scY":0.01,"x":-5.1625},"duration":28},{"tweenEasing":null,"transform":{"scX":1.9744,"y":5.19,"scY":1.9744,"x":-5.19},"duration":13}],"name":"mo"},{"frame":[{"tweenEasing":null,"transform":{},"duration":45}],"name":"guang1"},{"frame":[{"tweenEasing":null,"transform":{},"duration":45}],"name":"zti"},{"frame":[{"tweenEasing":null,"transform":{},"duration":45}],"name":"boom1"},{"frame":[{"tweenEasing":null,"transform":{},"duration":45}],"name":"guang"},{"frame":[{"tweenEasing":null,"transform":{},"duration":45}],"name":"chi1"}],"name":"peng","slot":[{"frame":[{"color":{},"displayIndex":-1,"tweenEasing":null,"duration":45}],"name":"moshui"},{"frame":[{"color":{},"tweenEasing":null,"duration":45}],"name":"modi"},{"frame":[{"color":{"aM":0},"displayIndex":1,"tweenEasing":null,"duration":6},{"color":{"aM":0},"displayIndex":1,"tweenEasing":0,"duration":1},{"color":{"aM":80},"displayIndex":1,"tweenEasing":null,"duration":10},{"color":{"aM":80},"displayIndex":1,"tweenEasing":0,"duration":12},{"color":{"aM":0},"displayIndex":1,"tweenEasing":null,"duration":16}],"name":"mo"},{"frame":[{"color":{},"displayIndex":3,"tweenEasing":null,"duration":45}],"name":"chi"},{"frame":[{"color":{"rM":91,"gM":54,"bM":33,"aM":0},"displayIndex":2,"tweenEasing":null,"duration":4},{"color":{"rM":91,"gM":54,"bM":33,"aM":0},"displayIndex":2,"tweenEasing":0,"duration":3},{"color":{"rM":91,"gM":54,"bM":33},"displayIndex":2,"tweenEasing":null,"duration":9},{"color":{"rM":91,"gM":54,"bM":33},"displayIndex":2,"tweenEasing":0,"duration":7},{"color":{"rM":91,"gM":54,"bM":33,"aM":0},"displayIndex":2,"tweenEasing":null,"duration":22}],"name":"chig"},{"frame":[{"color":{},"displayIndex":-1,"tweenEasing":null,"duration":45}],"name":"guang"}]},{"ffd":[],"frame":[],"playTimes":0,"duration":45,"bone":[{"frame":[{"tweenEasing":null,"transform":{},"duration":45}],"name":"root"},{"frame":[{"curve":[0.234,0.008,1,1],"transform":{"scX":1.5,"scY":1.5},"duration":5},{"tweenEasing":0,"transform":{"scX":0.3957,"scY":0.3957},"duration":5},{"tweenEasing":0,"transform":{"scX":1.4175,"scY":1.4175,"x":1.13},"duration":10},{"tweenEasing":0,"transform":{},"duration":25},{"tweenEasing":null,"transform":{},"duration":0}],"name":"chi"},{"frame":[{"tweenEasing":null,"transform":{"scX":0.4856,"scY":0.4856},"duration":4},{"tweenEasing":0,"transform":{"scX":0.4856,"y":-4.44,"scY":0.4856,"x":-3.33},"duration":7},{"tweenEasing":0,"transform":{"scX":1.3434,"y":-0.11,"scY":1.3434,"x":-7.2932},"duration":13},{"tweenEasing":null,"transform":{"scX":1.5915,"y":1.7162,"scY":1.5915,"x":-5.95},"duration":21}],"name":"szi"},{"frame":[{"tweenEasing":null,"transform":{},"duration":4},{"curve":[0,0,0.81,0.995],"transform":{"scX":0.01,"y":7.7437,"scY":0.01,"x":-5.1625},"duration":28},{"tweenEasing":null,"transform":{"scX":1.9744,"y":5.19,"scY":1.9744,"x":-5.19},"duration":13}],"name":"mo"},{"frame":[{"tweenEasing":null,"transform":{},"duration":45}],"name":"guang1"},{"frame":[{"tweenEasing":null,"transform":{},"duration":45}],"name":"zti"},{"frame":[{"tweenEasing":null,"transform":{},"duration":45}],"name":"boom1"},{"frame":[{"tweenEasing":null,"transform":{},"duration":45}],"name":"guang"},{"frame":[{"tweenEasing":null,"transform":{},"duration":45}],"name":"chi1"}],"name":"ti","slot":[{"frame":[{"color":{},"displayIndex":-1,"tweenEasing":null,"duration":45}],"name":"moshui"},{"frame":[{"color":{},"tweenEasing":null,"duration":45}],"name":"modi"},{"frame":[{"color":{"aM":0},"displayIndex":1,"tweenEasing":null,"duration":6},{"color":{"aM":0},"displayIndex":1,"tweenEasing":0,"duration":1},{"color":{"aM":80},"displayIndex":1,"tweenEasing":null,"duration":10},{"color":{"aM":80},"displayIndex":1,"tweenEasing":0,"duration":12},{"color":{"aM":0},"displayIndex":1,"tweenEasing":null,"duration":16}],"name":"mo"},{"frame":[{"color":{},"displayIndex":4,"tweenEasing":null,"duration":45}],"name":"chi"},{"frame":[{"color":{"rM":91,"gM":54,"bM":33,"aM":0},"displayIndex":1,"tweenEasing":null,"duration":4},{"color":{"rM":91,"gM":54,"bM":33,"aM":0},"displayIndex":1,"tweenEasing":0,"duration":3},{"color":{"rM":91,"gM":54,"bM":33},"displayIndex":1,"tweenEasing":null,"duration":9},{"color":{"rM":91,"gM":54,"bM":33},"displayIndex":1,"tweenEasing":0,"duration":7},{"color":{"rM":91,"gM":54,"bM":33,"aM":0},"displayIndex":1,"tweenEasing":null,"duration":22}],"name":"chig"},{"frame":[{"color":{},"displayIndex":-1,"tweenEasing":null,"duration":45}],"name":"guang"}]},{"ffd":[],"frame":[],"playTimes":0,"duration":45,"bone":[{"frame":[{"tweenEasing":null,"transform":{},"duration":45}],"name":"root"},{"frame":[{"curve":[0.234,0.008,1,1],"transform":{"scX":1.5,"scY":1.5},"duration":5},{"tweenEasing":0,"transform":{"scX":0.3957,"scY":0.3957},"duration":5},{"tweenEasing":0,"transform":{"scX":1.4175,"scY":1.4175,"x":1.13},"duration":10},{"tweenEasing":0,"transform":{},"duration":25},{"tweenEasing":null,"transform":{},"duration":0}],"name":"chi"},{"frame":[{"tweenEasing":null,"transform":{"scX":0.4856,"scY":0.4856},"duration":4},{"tweenEasing":0,"transform":{"scX":0.4856,"scY":0.4856,"x":5.28},"duration":7},{"tweenEasing":0,"transform":{"scX":1.3434,"scY":1.3434,"x":2.8268},"duration":13},{"tweenEasing":null,"transform":{"scX":1.5915,"y":2.0262,"scY":1.5915,"x":5.28},"duration":21}],"name":"szi"},{"frame":[{"tweenEasing":null,"transform":{},"duration":4},{"curve":[0,0,0.81,0.995],"transform":{"scX":0.01,"y":7.7437,"scY":0.01,"x":-5.1625},"duration":28},{"tweenEasing":null,"transform":{"scX":1.9744,"y":5.19,"scY":1.9744,"x":-5.19},"duration":13}],"name":"mo"},{"frame":[{"tweenEasing":null,"transform":{},"duration":45}],"name":"guang1"},{"frame":[{"tweenEasing":null,"transform":{},"duration":45}],"name":"zti"},{"frame":[{"tweenEasing":null,"transform":{},"duration":45}],"name":"boom1"},{"frame":[{"tweenEasing":null,"transform":{},"duration":45}],"name":"guang"},{"frame":[{"tweenEasing":null,"transform":{},"duration":45}],"name":"chi1"}],"name":"gang","slot":[{"frame":[{"color":{},"displayIndex":-1,"tweenEasing":null,"duration":45}],"name":"moshui"},{"frame":[{"color":{},"tweenEasing":null,"duration":45}],"name":"modi"},{"frame":[{"color":{"aM":0},"displayIndex":1,"tweenEasing":null,"duration":6},{"color":{"aM":0},"displayIndex":1,"tweenEasing":0,"duration":1},{"color":{"aM":80},"displayIndex":1,"tweenEasing":null,"duration":10},{"color":{"aM":80},"displayIndex":1,"tweenEasing":0,"duration":12},{"color":{"aM":0},"displayIndex":1,"tweenEasing":null,"duration":16}],"name":"mo"},{"frame":[{"color":{},"displayIndex":2,"tweenEasing":null,"duration":45}],"name":"chi"},{"frame":[{"color":{"rM":91,"gM":54,"bM":33,"aM":0},"displayIndex":3,"tweenEasing":null,"duration":4},{"color":{"rM":91,"gM":54,"bM":33,"aM":0},"displayIndex":3,"tweenEasing":0,"duration":3},{"color":{"rM":91,"gM":54,"bM":33},"displayIndex":3,"tweenEasing":null,"duration":9},{"color":{"rM":91,"gM":54,"bM":33},"displayIndex":3,"tweenEasing":0,"duration":7},{"color":{"rM":91,"gM":54,"bM":33,"aM":0},"displayIndex":3,"tweenEasing":null,"duration":22}],"name":"chig"},{"frame":[{"color":{},"displayIndex":-1,"tweenEasing":null,"duration":45}],"name":"guang"}]},{"ffd":[],"frame":[],"playTimes":0,"duration":45,"bone":[{"frame":[{"tweenEasing":null,"transform":{},"duration":45}],"name":"root"},{"frame":[{"curve":[0.234,0.008,1,1],"transform":{"scX":1.5,"scY":1.5},"duration":4},{"tweenEasing":0,"transform":{"scX":0.3957,"scY":0.3957},"duration":5},{"tweenEasing":0,"transform":{"scX":1.4175,"scY":1.4175,"x":1.13},"duration":8},{"tweenEasing":0,"transform":{},"duration":28},{"tweenEasing":null,"transform":{},"duration":0}],"name":"chi"},{"frame":[{"tweenEasing":null,"transform":{"scX":0.4856,"scY":0.4856},"duration":3},{"tweenEasing":0,"transform":{"scX":0.4856,"scY":0.4856},"duration":7},{"tweenEasing":0,"transform":{"scX":1.3434,"y":6.55,"scY":1.3434,"x":-5.0732},"duration":11},{"tweenEasing":null,"transform":{"scX":1.5915,"y":7.2662,"scY":1.5915,"x":-2.62},"duration":24}],"name":"szi"},{"frame":[{"tweenEasing":null,"transform":{},"duration":4},{"curve":[0,0,0.676,0.99],"transform":{"scX":0.6205,"y":0.617,"scY":0.6205,"x":1.9643},"duration":28},{"tweenEasing":null,"transform":{"scX":1.7269,"y":-0.8831,"scY":1.7269,"x":-2.37},"duration":13}],"name":"mo"},{"frame":[{"tweenEasing":0,"transform":{"scX":0.9556,"scY":0.9556,"skX":-49.0404,"skY":-49.0404},"duration":8},{"tweenEasing":null,"transform":{"skX":98.0987,"skY":98.0987},"duration":37}],"name":"guang1"},{"frame":[{"tweenEasing":null,"transform":{},"duration":45}],"name":"zti"},{"frame":[{"tweenEasing":0,"transform":{},"duration":5},{"tweenEasing":0,"transform":{"scX":0.6557,"scY":0.6557},"duration":9},{"tweenEasing":0,"transform":{"scX":1.4244,"scY":1.4244},"duration":21},{"tweenEasing":null,"transform":{"scX":1.6588,"scY":1.6588},"duration":10}],"name":"boom1"},{"frame":[{"tweenEasing":0,"transform":{"scX":3.2277,"scY":3.2277},"duration":8},{"tweenEasing":null,"transform":{"scX":0.3927,"y":-2.3055,"scY":0.3927},"duration":37}],"name":"guang"},{"frame":[{"tweenEasing":null,"transform":{"scX":1.1385,"y":-17.1463,"scY":1.1385,"skX":90,"skY":90,"x":-18.3992},"duration":8},{"tweenEasing":0,"transform":{"scX":1.1385,"y":-17.1463,"scY":1.1385,"skX":90,"skY":90,"x":-18.3992},"duration":8},{"tweenEasing":0,"transform":{"scX":1.4103,"y":-17.1463,"scY":1.4103,"skX":90,"skY":90,"x":-18.3992},"duration":10},{"tweenEasing":null,"transform":{"scX":1.5308,"y":-17.1463,"scY":1.5308,"skX":90,"skY":90,"x":-18.3992},"duration":19}],"name":"chi1"}],"name":"hu","slot":[{"frame":[{"color":{},"tweenEasing":null,"duration":45}],"name":"moshui"},{"frame":[{"color":{},"displayIndex":-1,"tweenEasing":null,"duration":45}],"name":"modi"},{"frame":[{"color":{"aM":0},"tweenEasing":null,"duration":4},{"color":{"aM":0},"tweenEasing":0,"duration":3},{"color":{"aM":25},"tweenEasing":0,"duration":12},{"color":{"aM":25},"tweenEasing":0,"duration":10},{"color":{"aM":0},"tweenEasing":null,"duration":16}],"name":"mo"},{"frame":[{"color":{},"displayIndex":1,"tweenEasing":null,"duration":45}],"name":"chi"},{"frame":[{"color":{"rM":91,"gM":54,"bM":33,"aM":0},"displayIndex":1,"tweenEasing":null,"duration":3},{"color":{"rM":91,"gM":54,"bM":33,"aM":0},"displayIndex":1,"tweenEasing":0,"duration":3},{"color":{"rM":91,"gM":54,"bM":33},"displayIndex":1,"tweenEasing":null,"duration":8},{"color":{"rM":91,"gM":54,"bM":33},"displayIndex":1,"tweenEasing":0,"duration":6},{"color":{"rM":91,"gM":54,"bM":33,"aM":0},"displayIndex":1,"tweenEasing":null,"duration":25}],"name":"chig"},{"frame":[{"color":{"aM":63},"tweenEasing":0,"duration":6},{"color":{"aM":63},"tweenEasing":0,"duration":2},{"color":{"aM":0},"tweenEasing":null,"duration":37}],"name":"guang"}]}]}],"isGlobal":0,"name":"yuanzi","version":"4.5"}