{"frameRate":30,"isGlobal":0,"armature":[{"animation":[{"duration":45,"frame":[],"playTimes":0,"slot":[{"frame":[{"duration":45,"tweenEasing":null,"displayIndex":3,"color":{}}],"name":"dian"},{"frame":[{"duration":45,"tweenEasing":null,"color":{}}],"name":"dian1"},{"frame":[{"duration":45,"tweenEasing":null,"color":{}}],"name":"dian11"},{"frame":[{"duration":45,"tweenEasing":null,"displayIndex":3,"color":{}}],"name":"dian111"},{"frame":[{"duration":45,"tweenEasing":null,"color":{}}],"name":"dian1111"},{"frame":[{"duration":45,"tweenEasing":null,"displayIndex":2,"color":{}}],"name":"dian11111"},{"frame":[{"duration":45,"tweenEasing":null,"displayIndex":2,"color":{}}],"name":"dian111111"},{"frame":[{"duration":45,"tweenEasing":null,"displayIndex":2,"color":{}}],"name":"dian1111111"}],"ffd":[],"name":"newAnimation","bone":[{"frame":[{"duration":45,"tweenEasing":null,"transform":{}}],"name":"root"},{"frame":[{"duration":5,"tweenEasing":0,"transform":{}},{"duration":5,"tweenEasing":0,"transform":{"y":-8.0269}},{"duration":35,"tweenEasing":null,"transform":{}}],"name":"youxi"},{"frame":[{"duration":45,"tweenEasing":null,"transform":{}}],"name":"zti"},{"frame":[{"duration":5,"tweenEasing":null,"transform":{}},{"duration":5,"tweenEasing":0,"transform":{}},{"duration":5,"tweenEasing":0,"transform":{"y":-8.0269}},{"duration":30,"tweenEasing":null,"transform":{}}],"name":"youxi1"},{"frame":[{"duration":10,"tweenEasing":null,"transform":{}},{"duration":5,"tweenEasing":0,"transform":{}},{"duration":5,"tweenEasing":0,"transform":{"y":-8.0269}},{"duration":25,"tweenEasing":null,"transform":{}}],"name":"youxi11"},{"frame":[{"duration":15,"tweenEasing":null,"transform":{"x":0.92}},{"duration":5,"tweenEasing":0,"transform":{"x":0.92}},{"duration":5,"tweenEasing":0,"transform":{"y":-8.0269,"x":0.92}},{"duration":20,"tweenEasing":null,"transform":{"x":0.92}}],"name":"youxi111"},{"frame":[{"duration":20,"tweenEasing":null,"transform":{"x":0.92}},{"duration":5,"tweenEasing":0,"transform":{"x":0.92}},{"duration":5,"tweenEasing":0,"transform":{"y":-8.0269,"x":0.92}},{"duration":15,"tweenEasing":null,"transform":{"x":0.92}}],"name":"youxi1111"},{"frame":[{"duration":25,"tweenEasing":null,"transform":{"x":0.92}},{"duration":5,"tweenEasing":0,"transform":{"x":0.92}},{"duration":5,"tweenEasing":0,"transform":{"y":-8.0269,"x":0.92}},{"duration":10,"tweenEasing":null,"transform":{"x":0.92}}],"name":"youxi11111"},{"frame":[{"duration":30,"tweenEasing":null,"transform":{"x":0.92}},{"duration":5,"tweenEasing":0,"transform":{"x":0.92}},{"duration":5,"tweenEasing":0,"transform":{"y":-8.0269,"x":0.92}},{"duration":5,"tweenEasing":null,"transform":{"x":0.92}}],"name":"youxi111111"},{"frame":[{"duration":35,"tweenEasing":null,"transform":{"x":0.92}},{"duration":5,"tweenEasing":0,"transform":{"x":0.92}},{"duration":5,"tweenEasing":0,"transform":{"y":-8.0269,"x":0.92}},{"duration":0,"tweenEasing":null,"transform":{"x":0.92}}],"name":"youxi1111111"}]}],"type":"Armature","name":"Armature","ik":[],"aabb":{"width":188.36999999999972,"y":-16,"height":32,"x":-16},"skin":[{"slot":[{"display":[{"type":"image","name":"xi","transform":{}},{"type":"image","name":"dian","transform":{}},{"type":"image","name":"zhong","transform":{}},{"type":"image","name":"jia","transform":{}},{"type":"image","name":"zha","transform":{}},{"type":"image","name":"y","transform":{}}],"name":"dian1"},{"display":[{"type":"image","name":"zhong","transform":{}},{"type":"image","name":"xi","transform":{}},{"type":"image","name":"dian","transform":{}},{"type":"image","name":"zha","transform":{}},{"type":"image","name":"jia","transform":{}},{"type":"image","name":"y","transform":{}}],"name":"dian1111111"},{"display":[{"type":"image","name":"zhong","transform":{}},{"type":"image","name":"y","transform":{}},{"type":"image","name":"dian","transform":{}},{"type":"image","name":"xi","transform":{}},{"type":"image","name":"zha","transform":{}},{"type":"image","name":"jia","transform":{}}],"name":"dian11111"},{"display":[{"type":"image","name":"dian","transform":{}},{"type":"image","name":"zhong","transform":{}},{"type":"image","name":"zha","transform":{}},{"type":"image","name":"y","transform":{}},{"type":"image","name":"xi","transform":{}},{"type":"image","name":"jia","transform":{}}],"name":"dian"},{"display":[{"type":"image","name":"xi","transform":{}},{"type":"image","name":"jia","transform":{}},{"type":"image","name":"y","transform":{}},{"type":"image","name":"zha","transform":{}},{"type":"image","name":"dian","transform":{}},{"type":"image","name":"zhong","transform":{}}],"name":"dian111"},{"display":[{"type":"image","name":"jia","transform":{}},{"type":"image","name":"zha","transform":{}},{"type":"image","name":"y","transform":{}},{"type":"image","name":"zhong","transform":{}},{"type":"image","name":"xi","transform":{}},{"type":"image","name":"dian","transform":{}}],"name":"dian11"},{"display":[{"type":"image","name":"zhong","transform":{}},{"type":"image","name":"dian","transform":{}},{"type":"image","name":"xi","transform":{}},{"type":"image","name":"y","transform":{}},{"type":"image","name":"jia","transform":{}},{"type":"image","name":"zha","transform":{}}],"name":"dian1111"},{"display":[{"type":"image","name":"zhong","transform":{}},{"type":"image","name":"zha","transform":{}},{"type":"image","name":"dian","transform":{}},{"type":"image","name":"jia","transform":{}},{"type":"image","name":"xi","transform":{}},{"type":"image","name":"y","transform":{}}],"name":"dian111111"}],"name":""}],"defaultActions":[{"gotoAndPlay":"newAnimation"}],"bone":[{"name":"root","transform":{}},{"transform":{},"name":"zti","parent":"root"},{"transform":{},"name":"youxi","parent":"zti"},{"transform":{"x":32.1631},"name":"youxi1","parent":"zti"},{"transform":{"x":61.6051},"name":"youxi11","parent":"zti"},{"transform":{"x":92.4998},"name":"youxi111","parent":"zti"},{"transform":{"x":122.8754},"name":"youxi1111","parent":"zti"},{"transform":{"y":4.6827,"x":143.3554},"name":"youxi11111","parent":"zti"},{"transform":{"y":4.68,"skX":-0.0701,"skY":-0.0701,"x":155.8909},"name":"youxi111111","parent":"zti"},{"transform":{"y":4.68,"skX":-0.0701,"skY":-0.0701,"x":168.37},"name":"youxi1111111","parent":"zti"}],"frameRate":30,"slot":[{"color":{},"displayIndex":3,"name":"dian","parent":"youxi"},{"z":1,"color":{},"name":"dian1","parent":"youxi1"},{"z":2,"color":{},"name":"dian11","parent":"youxi11"},{"z":3,"color":{},"displayIndex":5,"name":"dian111","parent":"youxi111"},{"z":4,"color":{},"name":"dian1111","parent":"youxi1111"},{"z":5,"color":{},"displayIndex":2,"name":"dian11111","parent":"youxi11111"},{"z":6,"color":{},"displayIndex":2,"name":"dian111111","parent":"youxi111111"},{"z":7,"color":{},"displayIndex":2,"name":"dian1111111","parent":"youxi1111111"}]}],"name":"jiazhai","version":"4.5"}